concrete_toto-0.0.11-py3.9-nspkg.pth
concrete/toto/__init__.py
concrete/toto/file.py
concrete_toto-0.0.11.dist-info/LICENSE
concrete_toto-0.0.11.dist-info/METADATA
concrete_toto-0.0.11.dist-info/WHEEL
concrete_toto-0.0.11.dist-info/namespace_packages.txt
concrete_toto-0.0.11.dist-info/top_level.txt
concrete_toto-0.0.11.dist-info/RECORD
